{
    "活動名稱": "10 5年度 籌募『 防癆基金 及結核病患醫療生活補助 款』",
    "活動許可文號": "104.12.17衛部救字第1041363520號函",
    "勸募活動開始": "105\/01\/01",
    "勸募活動結束": "105\/12\/31",
    "預募金額": "1,400,000元",
    "實募金額": "0元",
    "瀏覽人次": "55",
    "點擊率": "0.02%",
    "申請單位": "社團法人中華民國防癆協會",
    "所屬團體": "公益性社團法人",
    "立案許可日期文號": "046\/09\/06 台內社字第12069號函",
    "募款用途": "籌募『 防癆基金 及結核病患醫療生活補助 款』所需經費",
    "公益目的": "為籌募本會『防癆基金及結核病患醫療生活補助款』所需經費新台幣 壹佰肆拾萬元整，嘉惠結核病患，早日康復，杜絕傳染源，維護國民 健康。",
    "活動地區": "全國",
    "勸募活動申請表": "http:\/\/sasw.mohw.gov.tw\/app39\/solicitView\/applicationForm\/269824056",
    "勸募活動計畫書": "http:\/\/sasw.mohw.gov.tw\/app39\/solicitView\/planForm\/269824056",
    "勸募活動財物使用計畫書": "http:\/\/sasw.mohw.gov.tw\/app39\/solicitView\/financeForm\/269824056",
    "徵信方式": "依法開立收據，活動結束後，辦理情形及捐款明細除報請主管機關備查外，另徵信錄刊登於本會網站（http:\/\/ntbatpe.myweb.hinet.net\/）。",
    "勸募方式": "其他：自由捐款認購防癆慈善紀念票、委託中華郵政股份有限公司代售及舉辦義賣活動",
    "捐款專戶": "銀行名稱：第一商業銀行，分行名稱：圓山分行\r\n                        帳號：14010035635",
    "成果備查文號": "",
    "成果備查報告書": "",
    "捐贈人資料": "",
    "結案備查文號": "",
    "支出明細": "",
    "執行（服務）成果報告": "",
    "使用情形成果報告": "",
    "結案備查報告書": ""
}