{
    "活動名稱": "105年度書香泰源-貧困孩童餐費及就學學費服務計畫",
    "活動許可文號": "104.12.30衛部救字第1041363747號函",
    "勸募活動開始": "105\/01\/01",
    "勸募活動結束": "105\/12\/31",
    "預募金額": "6,000,000元",
    "實募金額": "191,581元",
    "瀏覽人次": "71",
    "點擊率": "0.03%",
    "申請單位": "社團法人台東縣原住民嘎屋啦瀚文教發展協會",
    "所屬團體": "公益性社團法人",
    "立案許可日期文號": "099\/10\/20 民國99年10月20日府社行字第0990114238號",
    "募款用途": "偏鄉地區貧困孩童之就學學費、營養午\/晚餐(含假日)、獎學金設立",
    "公益目的": "為籌募「105年度書香泰源-貧困孩童餐費及就學學費服務計畫」需經費新臺幣陸佰萬元整，辦理偏鄉地區貧困孩童就學學費、餐費、交通服務計劃。",
    "活動地區": "全國",
    "勸募活動申請表": "http:\/\/sasw.mohw.gov.tw\/app39\/solicitView\/applicationForm\/269842628",
    "勸募活動計畫書": "http:\/\/sasw.mohw.gov.tw\/app39\/solicitView\/planForm\/269842628",
    "勸募活動財物使用計畫書": "http:\/\/sasw.mohw.gov.tw\/app39\/solicitView\/financeForm\/269842628",
    "徵信方式": "活動結束後，辦理情形及捐款明細除報請主管機關備查外，另刊登於本會網站（http:\/\/kaulahan.org.tw\/domation）。",
    "勸募方式": "其他：針對各機關團體、參與其他組織之活動、全國各地景點商家設置募款箱、本會及網路募款平台、搭配大眾所捐贈，或本會所生產之義賣品進行勸募、參與其他非營利組織舉辦之活動，對社會大眾進行勸募。",
    "捐款專戶": "銀行名稱：合作金庫，分行名稱：台東分行\r\n                        帳號：0390717392372",
    "成果備查文號": "",
    "成果備查報告書": "",
    "捐贈人資料": "",
    "結案備查文號": "",
    "支出明細": "",
    "執行（服務）成果報告": "",
    "使用情形成果報告": "",
    "結案備查報告書": ""
}